kore_plugins_ptvsd/__init__.py
kore_plugins_ptvsd/plugins/__init__.py
kore_plugins_ptvsd/plugins/ptvsd.py
kore_plugins_ptvsd-0.0.1.dist-info/DESCRIPTION.rst
kore_plugins_ptvsd-0.0.1.dist-info/METADATA
kore_plugins_ptvsd-0.0.1.dist-info/RECORD
kore_plugins_ptvsd-0.0.1.dist-info/WHEEL
kore_plugins_ptvsd-0.0.1.dist-info/entry_points.txt
kore_plugins_ptvsd-0.0.1.dist-info/metadata.json
kore_plugins_ptvsd-0.0.1.dist-info/top_level.txt
